epub2md/__init__.py
epub2md-0.1.5.dist-info/WHEEL
epub2md-0.1.5.dist-info/entry_points.txt
epub2md-0.1.5.dist-info/METADATA
epub2md-0.1.5.dist-info/RECORD
