Metadata-Version: 2.3
Name: epub2md
Version: 0.1.5
Summary: Convert EPUB to clean Markdown chapters
Requires-Python: >=3.8
Project-URL: Repository, https://github.com/mefengl/epub2md
